[{"id":"6cdf9879.8a3728","type":"tab","label":"Flow 1","disabled":false,"info":""},{"id":"fdf853b9.b8666","type":"inject","z":"6cdf9879.8a3728","name":"","props":[{"p":"payload"},{"p":"topic","vt":"str"}],"repeat":"1","crontab":"","once":true,"onceDelay":0.1,"topic":"","payload":"","payloadType":"date","x":110,"y":500,"wires":[["7b311132.7f1e9","b408134b.05b21","83a0e707.1f48a8","f1024452.1dcce8","5a2d2769.98b1c8","bc8f1e6a.f0c3e","dfdc69db.8c7218"]]},{"id":"7b311132.7f1e9","type":"file in","z":"6cdf9879.8a3728","name":"Xdot","filename":"/home/pi/mxet300_lab/basics/mxet300_lab_x_dot.txt","format":"utf8","chunk":false,"sendError":false,"encoding":"none","x":410,"y":500,"wires":[["6a65d7d9.ef4678"]]},{"id":"6a65d7d9.ef4678","type":"ui_chart","z":"6cdf9879.8a3728","name":"","group":"d6f9dfd7.c8b6","order":1,"width":0,"height":0,"label":"Forward Velocity (m/s)","chartType":"line","legend":"false","xformat":"HH:mm:ss","interpolate":"linear","nodata":"","dot":false,"ymin":"","ymax":"","removeOlder":"30","removeOlderPoints":"","removeOlderUnit":"1","cutout":0,"useOneColor":false,"useUTC":false,"colors":["#1f77b4","#aec7e8","#ff7f0e","#2ca02c","#98df8a","#d62728","#ff9896","#9467bd","#c5b0d5"],"outputs":1,"useDifferentColor":false,"x":640,"y":500,"wires":[[]]},{"id":"b408134b.05b21","type":"file in","z":"6cdf9879.8a3728","name":"Theta Dot","filename":"/home/pi/mxet300_lab/basics/mxet300_lab_theta_dot.txt","format":"utf8","chunk":false,"sendError":false,"encoding":"none","x":420,"y":560,"wires":[["b4f980d5.735d3"]]},{"id":"b4f980d5.735d3","type":"ui_chart","z":"6cdf9879.8a3728","name":"","group":"d6f9dfd7.c8b6","order":2,"width":0,"height":0,"label":"Angular Velocity (rad/s)","chartType":"line","legend":"false","xformat":"HH:mm:ss","interpolate":"linear","nodata":"","dot":false,"ymin":"","ymax":"","removeOlder":"30","removeOlderPoints":"","removeOlderUnit":"1","cutout":0,"useOneColor":false,"useUTC":false,"colors":["#1f77b4","#aec7e8","#ff7f0e","#2ca02c","#98df8a","#d62728","#ff9896","#9467bd","#c5b0d5"],"outputs":1,"useDifferentColor":false,"x":650,"y":560,"wires":[[]]},{"id":"83a0e707.1f48a8","type":"file in","z":"6cdf9879.8a3728","name":"Pi Voltage","filename":"/home/pi/mxet300_lab/basics/mxet300_labvoltage_val.txt","format":"utf8","chunk":false,"sendError":false,"encoding":"none","x":350,"y":660,"wires":[["5ba5a8da.9e0358"]]},{"id":"5ba5a8da.9e0358","type":"ui_gauge","z":"6cdf9879.8a3728","name":"Voltage","group":"bed244d8.06cc38","order":0,"width":"0","height":"0","gtype":"gage","title":"Battery Voltage","label":"V","format":"{{value}}","min":0,"max":"12","colors":["#b30000","#e6e600","#1eff00"],"seg1":"","seg2":"","x":530,"y":640,"wires":[]},{"id":"f1024452.1dcce8","type":"file in","z":"6cdf9879.8a3728","name":"Cardinal","filename":"/home/pi/mxet300_lab/basics/mxet300_labcompass_direction.txt","format":"utf8","chunk":false,"sendError":false,"encoding":"none","x":350,"y":700,"wires":[["1f567b6c.c42e95"]]},{"id":"1f567b6c.c42e95","type":"ui_text","z":"6cdf9879.8a3728","group":"81f0d90e.fd7e28","order":1,"width":0,"height":0,"name":"","label":"Cardinal Direction: ","format":"{{msg.payload}}","layout":"row-center","x":560,"y":700,"wires":[]},{"id":"5a2d2769.98b1c8","type":"file in","z":"6cdf9879.8a3728","name":"Coordinates","filename":"/home/pi/mxet300_lab/basics/mxet300_labcompass_direction_val.txt","format":"utf8","chunk":false,"sendError":false,"encoding":"none","x":360,"y":740,"wires":[["9afd5dbf.7148c"]]},{"id":"9afd5dbf.7148c","type":"ui_gauge","z":"6cdf9879.8a3728","name":"Compass","group":"81f0d90e.fd7e28","order":0,"width":0,"height":0,"gtype":"compass","title":"Compass","label":"Degrees","format":"{{value}}","min":"-180","max":"180","colors":["#00b500","#e6e600","#ca3838"],"seg1":"","seg2":"","x":530,"y":740,"wires":[]},{"id":"bc8f1e6a.f0c3e","type":"file in","z":"6cdf9879.8a3728","name":"PDL","filename":"/home/pi/mxet300_lab/basics/mxet300_labpdl.txt","format":"utf8","chunk":false,"sendError":false,"encoding":"none","x":360,"y":820,"wires":[["d5325d2.05103a"]]},{"id":"dfdc69db.8c7218","type":"file in","z":"6cdf9879.8a3728","name":"PDR","filename":"/home/pi/mxet300_lab/basics/mxet300_labpdr.txt","format":"utf8","chunk":false,"sendError":false,"encoding":"none","x":350,"y":860,"wires":[["3a94b8be.4b9648"]]},{"id":"d5325d2.05103a","type":"ui_chart","z":"6cdf9879.8a3728","name":"","group":"d2f0acf2.ab564","order":0,"width":0,"height":0,"label":"Left Wheel (rads/s)","chartType":"line","legend":"false","xformat":"HH:mm:ss","interpolate":"linear","nodata":"","dot":false,"ymin":"","ymax":"","removeOlder":"30","removeOlderPoints":"","removeOlderUnit":"1","cutout":0,"useOneColor":false,"useUTC":false,"colors":["#1f77b4","#aec7e8","#ff7f0e","#2ca02c","#98df8a","#d62728","#ff9896","#9467bd","#c5b0d5"],"outputs":1,"useDifferentColor":false,"x":600,"y":820,"wires":[[]]},{"id":"3a94b8be.4b9648","type":"ui_chart","z":"6cdf9879.8a3728","name":"","group":"d2f0acf2.ab564","order":1,"width":0,"height":0,"label":"Right Wheel (rads/s)","chartType":"line","legend":"false","xformat":"HH:mm:ss","interpolate":"linear","nodata":"","dot":false,"ymin":"","ymax":"","removeOlder":"30","removeOlderPoints":"","removeOlderUnit":"1","cutout":0,"useOneColor":false,"useUTC":false,"colors":["#1f77b4","#aec7e8","#ff7f0e","#2ca02c","#98df8a","#d62728","#ff9896","#9467bd","#c5b0d5"],"outputs":1,"useDifferentColor":false,"x":630,"y":880,"wires":[[]]},{"id":"d6f9dfd7.c8b6","type":"ui_group","name":"Chassis Speed","tab":"da434eb9.c05d5","order":4,"disp":true,"width":"6","collapse":false},{"id":"bed244d8.06cc38","type":"ui_group","name":"Voltage","tab":"da434eb9.c05d5","order":2,"disp":true,"width":"6","collapse":false},{"id":"81f0d90e.fd7e28","type":"ui_group","name":"Cardinal Coordinates","tab":"da434eb9.c05d5","order":1,"disp":true,"width":"6","collapse":false},{"id":"d2f0acf2.ab564","type":"ui_group","name":"Wheel Speeds","tab":"da434eb9.c05d5","order":3,"disp":true,"width":"6","collapse":false},{"id":"da434eb9.c05d5","type":"ui_tab","name":"Tab 2","icon":"dashboard","order":1}]